client/__init__.py
client/run_client.py
client/client/__init__.py
client/client/add_contacts_dialog.py
client/client/client_db.py
client/client/client_gui.py
client/client/client_main_window_convert.py
client/client/client_transport.py
client/client/delete_contact_dialog.py
client/client/start_dialog.py
client/commons/__init__.py
client/commons/commons.py
client/commons/decorators.py
client/commons/descryptors.py
client/commons/errors.py
client/commons/metaclasses.py
client/commons/utils.py
client/logs/__init__.py
messenger_client_with_gui-0.0.2.data/scripts/client_run
messenger_client_with_gui-0.0.2.dist-info/METADATA
messenger_client_with_gui-0.0.2.dist-info/WHEEL
messenger_client_with_gui-0.0.2.dist-info/top_level.txt
messenger_client_with_gui-0.0.2.dist-info/RECORD
